setup.py
diss_prob/Binomialdistribution.py
diss_prob/Gaussiandistribution.py
diss_prob/Generaldistribution.py
diss_prob/__init__.py
diss_prob.egg-info/PKG-INFO
diss_prob.egg-info/SOURCES.txt
diss_prob.egg-info/dependency_links.txt
diss_prob.egg-info/not-zip-safe
diss_prob.egg-info/top_level.txt