Metadata-Version: 1.0
Name: diss-prob
Version: 0.2
Summary: Gaussian distributions
Home-page: UNKNOWN
Author: Ose Daniel
Author-email: okojieose111@gmail.com
License: UNKNOWN
Platform: UNKNOWN
